ytApiTest
