Metadata-Version: 1.0
Name: ytApiTest
Version: 1.0.52
Summary: UNKNOWN
Home-page: https://github.com/fangyt/ytApiTest.git
Author: fyt
Author-email: fangyt@163.com
License: UNKNOWN
Platform: UNKNOWN
